registry_sweepers-1.1.0-py3.9-nspkg.pth
pds/registrysweepers/VERSION.txt
pds/registrysweepers/__init__.py
pds/registrysweepers/provenance.py
registry_sweepers-1.1.0.dist-info/LICENSE.md
registry_sweepers-1.1.0.dist-info/METADATA
registry_sweepers-1.1.0.dist-info/NOTICE.txt
registry_sweepers-1.1.0.dist-info/WHEEL
registry_sweepers-1.1.0.dist-info/namespace_packages.txt
registry_sweepers-1.1.0.dist-info/top_level.txt
registry_sweepers-1.1.0.dist-info/zip-safe
registry_sweepers-1.1.0.dist-info/RECORD
