Metadata-Version: 2.1
Name: registry-sweepers
Version: 1.1.0
Summary: A set of utility scripts which transform/augment PDS registry metadata to support additional capabilities.
Home-page: https://github.com/NASA-PDS/registry-sweepers
Download-URL: https://github.com/NASA-PDS/registry-sweepers/releases/
Author: PDS
Author-email: pds_operator@jpl.nasa.gov
License: apache-2.0
Keywords: pds,planetary data,registry
Classifier: Programming Language :: Python :: 3
Classifier: Programming Language :: Python :: 3.10
Classifier: License :: OSI Approved :: Apache Software License
Classifier: Operating System :: OS Independent
Requires-Python: >=3.9
License-File: LICENSE.md
License-File: NOTICE.txt
Requires-Dist: requests (~=2.28)
Provides-Extra: dev
Requires-Dist: black ; extra == 'dev'
Requires-Dist: flake8 ; extra == 'dev'
Requires-Dist: flake8-bugbear ; extra == 'dev'
Requires-Dist: flake8-docstrings ; extra == 'dev'
Requires-Dist: pep8-naming ; extra == 'dev'
Requires-Dist: mypy ; extra == 'dev'
Requires-Dist: pydocstyle ; extra == 'dev'
Requires-Dist: coverage ; extra == 'dev'
Requires-Dist: pytest ; extra == 'dev'
Requires-Dist: pytest-cov ; extra == 'dev'
Requires-Dist: pytest-watch ; extra == 'dev'
Requires-Dist: pytest-xdist ; extra == 'dev'
Requires-Dist: pre-commit ; extra == 'dev'
Requires-Dist: sphinx ; extra == 'dev'
Requires-Dist: sphinx-rtd-theme ; extra == 'dev'
Requires-Dist: tox ; extra == 'dev'
Requires-Dist: types-requests (~=2.28) ; extra == 'dev'
Requires-Dist: types-setuptools ; extra == 'dev'
